starrydb/__init__.py
starrydb/starrydb.py
starrydb-0.8.8.dist-info/LICENSE
starrydb-0.8.8.dist-info/METADATA
starrydb-0.8.8.dist-info/WHEEL
starrydb-0.8.8.dist-info/top_level.txt
starrydb-0.8.8.dist-info/RECORD
