Metadata-Version: 2.1
Name: starrydb
Version: 0.8.8
Summary: A NoSQL lightweight database.
Home-page: https://github.com/luoxi-github/starrydb
Author: Luo Xi
Author-email: rossi913@163.com
License: UNKNOWN
Platform: UNKNOWN
Classifier: Programming Language :: Python :: 3
Classifier: License :: OSI Approved :: MIT License
Classifier: Operating System :: OS Independent
Requires-Python: >=3.6
Requires-Dist: msgpack
Requires-Dist: pylibmc
